Metadata-Version: 2.1
Name: pycompilertoexe
Version: 4.6.13
Summary: A library for creating a terminal user interface
Author: Lolip0p
Author-email: Lolip0p <lolipopdev@gmail.com>
Classifier: Programming Language :: Python :: 3
Classifier: License :: OSI Approved :: MIT License
Classifier: Operating System :: OS Independent
Requires-Python: >3.6
License-File: LICENSE.txt
